{
    "type": "FeatureCollection",
    "features": [
        {
            "type": "Feature",
            "properties": {
                "name": "THREE MILE ISLAND-1",
                "desc": "<img style=\"max-width:100%;display:block;clear:both;\" src=\"http:\/\/climateviewer.org\/img\/gallery\/np\/3-mile-island.jpg\"\/><br><p><br>THREE MILE ISLAND, UNITED STATES OF AMERICA<br>Total power output (operational reactors and reactors under construction): 786 MW<br>Details of reactor unit: THREE MILE ISLAND-1<br>Reactor type: Pressurised Water Reactor<br>Current status: Operational<br>Power rating:&nbsp; 786 MW<br>Constructed in 1968<br>Connected to the electricity grid on: 1974-06-19<br>&nbsp;<br>Source of reactor data:&nbsp; IAEA Power Reactor Information System (<a href=\"http:\/\/www.iaea.org\/pris\/\" target=\"_blank\">PRIS<\/a>)<br>Get further information on this plant from its <a href=\"http:\/\/en.wikipedia.org\/wiki\/Three_mile_island\" target=\"_blank\">Wikipedia page<\/a>.<br>Created by Jim Lee of <a href=\"http:\/\/climateviewer.com\/\">ClimateViewer.com<\/a><\/p>"
            },
            "geometry": {
                "type": "Point",
                "coordinates": [
                    -76.7252207508,
                    40.1546536616
                ]
            }
        },
        {
            "type": "Feature",
            "properties": {
                "name": "THREE MILE ISLAND-2 (CLOSED)",
                "desc": "<img style=\"max-width:100%;display:block;clear:both;\" src=\"http:\/\/climateviewer.org\/img\/gallery\/np\/3-mile-island.jpg\"\/><br><p>Radiation Emissions and Cancer Inicidence Within 10 miles of the Three Mile Island nuclear accident, 1979.<\/p>Source: <a href=\"http:\/\/www.southernstudies.org\/2009\/04\/investigation-revelations-about-three-mile-island-disaster-raise-doubts-over-nuclear-plant-s\">Investigation: Revelations about Three Mile Island disaster raise doubts over nuclear plant safety<\/a><\/p><p><br>THREE MILE ISLAND, UNITED STATES OF AMERICA<br>Total power output (operational reactors and reactors under construction): 880 MW<br>Details of reactor unit: THREE MILE ISLAND-2<br>Reactor type: Pressurised Water Reactor<br>Current status: Decommissioned<br>Constructed: 01 Nov, 1969<br>Connected to the electricity grid on: 21 Apr, 1978<br>Permanent Shutdown Date: 28 Mar, 1979<br><br>NOTE: <a href=\"http:\/\/en.wikipedia.org\/wiki\/Three_mile_island#Accident\">Partial melt-down and radioactive release<\/a> occurred on March 28, 1979 as a result of a loss of coolant systems.<br>&nbsp;<br>Source of reactor data:&nbsp; IAEA Power Reactor Information System (<a href=\"http:\/\/www.iaea.org\/pris\/\" target=\"_blank\">PRIS<\/a>)<br><br>Radiation Emissions and Cancer Inicidence Within 10 miles of the Three Mile Island nuclear accident, 1979.<br>Source: <a href=\"http:\/\/www.southernstudies.org\/2009\/04\/investigation-revelations-about-three-mile-island-disaster-raise-doubts-over-nuclear-plant-s\">Investigation: Revelations about Three Mile Island disaster raise doubts over nuclear plant safety<\/a><br><br>Get further information on this plant from its <a href=\"http:\/\/en.wikipedia.org\/wiki\/Three_mile_island\" target=\"_blank\">Wikipedia page<\/a>.<br>Created by Jim Lee of <a href=\"http:\/\/climateviewer.com\/\">ClimateViewer.com<\/a><\/p><h3>Nuclear Reactors on <a href=\"http:\/\/climateviewer.com\/nuclear-power-plant-map.html\">ClimateViewer.com<\/a><\/h3>"
            },
            "geometry": {
                "type": "Point",
                "coordinates": [
                    -76.7252949558,
                    40.1532495019
                ]
            }
        }
    ]
}